[
  {
    "code": "ar-SA",
    "name": "Arabic",
    "direction": "rtl"
  },
  {
    "code": "de-DE",
    "name": "German",
    "direction": "ltr"
  },
  {
    "code": "en-US",
    "name": "English",
    "direction": "ltr"
  },
  {
    "code": "es-ES",
    "name": "Spanish",
    "direction": "ltr"
  },
  {
    "code": "fr-FR",
    "name": "French",
    "direction": "ltr"
  },
  {
    "code": "it-IT",
    "name": "Italian",
    "direction": "ltr"
  },
  {
    "code": "pt-BR",
    "name": "Portuguese",
    "direction": "ltr"
  },
  {
    "code": "ru-RU",
    "name": "Russian",
    "direction": "ltr"
  }
]